[
  {
    "name": "Detroit Lions",
    "normalized": "detroitlions",
    "team": "DET",
    "position": "HC"
  },
  {
    "name": "Kansas City Chiefs",
    "normalized": "kansascitychiefs",
    "team": "KC",
    "position": "HC"
  },
  {
    "name": "Baltimore Ravens",
    "normalized": "baltimoreravens",
    "team": "BAL",
    "position": "HC"
  },
  {
    "name": "San Francisco 49ers",
    "normalized": "sanfrancisco49ers",
    "team": "SF",
    "position": "HC"
  },
  {
    "name": "Buffalo Bills",
    "normalized": "buffalobills",
    "team": "BUF",
    "position": "HC"
  },
  {
    "name": "Minnesota Vikings",
    "normalized": "minnesotavikings",
    "team": "MIN",
    "position": "HC"
  },
  {
    "name": "Dallas Cowboys",
    "normalized": "dallascowboys",
    "team": "DAL",
    "position": "HC"
  },
  {
    "name": "Green Bay Packers",
    "normalized": "greenbaypackers",
    "team": "GB",
    "position": "HC"
  },
  {
    "name": "Miami Dolphins",
    "normalized": "miamidolphins",
    "team": "MIA",
    "position": "HC"
  },
  {
    "name": "New York Jets",
    "normalized": "newyorkjets",
    "team": "NYJ",
    "position": "HC"
  },
  {
    "name": "Philadelphia Eagles",
    "normalized": "philadelphiaeagles",
    "team": "PHI",
    "position": "HC"
  },
  {
    "name": "Washington Commanders",
    "normalized": "washingtoncommanders",
    "team": "WAS",
    "position": "HC"
  },
  {
    "name": "New Orleans Saints",
    "normalized": "neworleanssaints",
    "team": "NO",
    "position": "HC"
  },
  {
    "name": "Cincinnati Bengals",
    "normalized": "cincinnatibengals",
    "team": "CIN",
    "position": "HC"
  },
  {
    "name": "Houston Texans",
    "normalized": "houstontexans",
    "team": "HOU",
    "position": "HC"
  },
  {
    "name": "Tampa Bay Buccaneers",
    "normalized": "tampabaybuccaneers",
    "team": "TB",
    "position": "HC"
  },
  {
    "name": "Chicago Bears",
    "normalized": "chicagobears",
    "team": "CHI",
    "position": "HC"
  },
  {
    "name": "Seattle Seahawks",
    "normalized": "seattleseahawks",
    "team": "SEA",
    "position": "HC"
  },
  {
    "name": "Cleveland Browns",
    "normalized": "clevelandbrowns",
    "team": "CLE",
    "position": "HC"
  },
  {
    "name": "Indianapolis Colts",
    "normalized": "indianapoliscolts",
    "team": "IND",
    "position": "HC"
  },
  {
    "name": "Pittsburgh Steelers",
    "normalized": "pittsburghsteelers",
    "team": "PIT",
    "position": "HC"
  },
  {
    "name": "New York Giants",
    "normalized": "newyorkgiants",
    "team": "NYG",
    "position": "HC"
  },
  {
    "name": "Atlanta Falcons",
    "normalized": "atlantafalcons",
    "team": "ATL",
    "position": "HC"
  },
  {
    "name": "Los Angeles Chargers",
    "normalized": "losangeleschargers",
    "team": "LAC",
    "position": "HC"
  },
  {
    "name": "Carolina Panthers",
    "normalized": "carolinapanthers",
    "team": "CAR",
    "position": "HC"
  },
  {
    "name": "Tennessee Titans",
    "normalized": "tennesseetitans",
    "team": "TEN",
    "position": "HC"
  },
  {
    "name": "Los Angeles Rams",
    "normalized": "losangelesrams",
    "team": "LAR",
    "position": "HC"
  }
]